icesat2_tracks/__init__.py
icesat2_tracks/app.py
icesat2_tracks/clitools.py
icesat2_tracks/ICEsat2_SI_tools/__init__.py
icesat2_tracks/ICEsat2_SI_tools/angle_optimizer.py
icesat2_tracks/ICEsat2_SI_tools/beam_stats.py
icesat2_tracks/ICEsat2_SI_tools/convert_GPS_time.py
icesat2_tracks/ICEsat2_SI_tools/convert_julian.py
icesat2_tracks/ICEsat2_SI_tools/filter_regrid.py
icesat2_tracks/ICEsat2_SI_tools/generalized_FT.py
icesat2_tracks/ICEsat2_SI_tools/iotools.py
icesat2_tracks/ICEsat2_SI_tools/lanczos.py
icesat2_tracks/ICEsat2_SI_tools/read_ground_tracks.py
icesat2_tracks/ICEsat2_SI_tools/sliderule_converter_tools.py
icesat2_tracks/ICEsat2_SI_tools/spectral_estimates.py
icesat2_tracks/ICEsat2_SI_tools/spicke_remover.py
icesat2_tracks/ICEsat2_SI_tools/wave_tools.py
icesat2_tracks/ICEsat2_SI_tools - Copy/__init__.py
icesat2_tracks/ICEsat2_SI_tools - Copy/angle_optimizer.py
icesat2_tracks/ICEsat2_SI_tools - Copy/beam_stats.py
icesat2_tracks/ICEsat2_SI_tools - Copy/convert_GPS_time.py
icesat2_tracks/ICEsat2_SI_tools - Copy/convert_julian.py
icesat2_tracks/ICEsat2_SI_tools - Copy/filter_regrid.py
icesat2_tracks/ICEsat2_SI_tools - Copy/generalized_FT.py
icesat2_tracks/ICEsat2_SI_tools - Copy/iotools.py
icesat2_tracks/ICEsat2_SI_tools - Copy/lanczos.py
icesat2_tracks/ICEsat2_SI_tools - Copy/read_ground_tracks.py
icesat2_tracks/ICEsat2_SI_tools - Copy/sliderule_converter_tools.py
icesat2_tracks/ICEsat2_SI_tools - Copy/spectral_estimates.py
icesat2_tracks/ICEsat2_SI_tools - Copy/spicke_remover.py
icesat2_tracks/ICEsat2_SI_tools - Copy/wave_tools.py
icesat2_tracks/analysis/SA01b_download_tester.py
icesat2_tracks/analysis_db/A01b_ALT07_SHNH_variance_tester.py
icesat2_tracks/analysis_db/A02c_IOWAGA_thredds_prior.py
icesat2_tracks/analysis_db/B01_SL_load_single_file.py
icesat2_tracks/analysis_db/B02_make_spectra_gFT.py
icesat2_tracks/analysis_db/B03_plot_spectra_ov.py
icesat2_tracks/analysis_db/B04_angle.py
icesat2_tracks/analysis_db/B05_define_angle.py
icesat2_tracks-0.0.1.dist-info/LICENSE.txt
icesat2_tracks-0.0.1.dist-info/METADATA
icesat2_tracks-0.0.1.dist-info/WHEEL
icesat2_tracks-0.0.1.dist-info/entry_points.txt
icesat2_tracks-0.0.1.dist-info/top_level.txt
icesat2_tracks-0.0.1.dist-info/RECORD
